scmpompg/__init__.py
scmpompg/pommodule1.py
scmpompg/pommodule2.py
scmpompg-0.1.1.dist-info/METADATA
scmpompg-0.1.1.dist-info/WHEEL
scmpompg-0.1.1.dist-info/top_level.txt
scmpompg-0.1.1.dist-info/RECORD
