Metadata-Version: 2.4
Name: scmpompg
Version: 0.1.1
Summary: This is my first package. This package is related to number theory.
Home-page: https://github.com/kadisak/scmpompg
Author: A. Karnbanjong
Author-email: kpadisak@gmail.com
Requires-Python: >=3.8
Dynamic: author
Dynamic: author-email
Dynamic: description
Dynamic: description-content-type
Dynamic: home-page
Dynamic: requires-python
Dynamic: summary
